loadwavesurfer/__init__.py
loadwavesurfer/loadws.py
LoadWaveSurfer-1.0.1.dist-info/LICENSE
LoadWaveSurfer-1.0.1.dist-info/METADATA
LoadWaveSurfer-1.0.1.dist-info/WHEEL
LoadWaveSurfer-1.0.1.dist-info/top_level.txt
LoadWaveSurfer-1.0.1.dist-info/RECORD
