Metadata-Version: 2.1
Name: LoadWaveSurfer
Version: 1.0.1
Summary: Load and parse ephys data acquired using Janelia's WaveSurfer.
Author-email: Raul Mojica <rmojica@mit.edu>
License: MIT License
Project-URL: Homepage, https://github.com/ralbso/LoadWaveSurfer
Project-URL: Bug Tracker, https://github.com/ralbso/LoadWaveSurfer/issues
Keywords: wavesurfer,loader,parser
Classifier: License :: OSI Approved :: MIT License
Classifier: Programming Language :: Python
Classifier: Programming Language :: Python :: 3
Classifier: Operating System :: Microsoft :: Windows
Requires-Python: >=3.7
License-File: LICENSE
Requires-Dist: numpy (>=1.23.0)
Requires-Dist: pandas (>=1.4.0)
Requires-Dist: pywavesurfer (>=0.0.7)
Provides-Extra: dev
Requires-Dist: black ; extra == 'dev'
Requires-Dist: pytest ; extra == 'dev'
Requires-Dist: pip-tools ; extra == 'dev'
